docs2vecs/__init__.py
docs2vecs/__main__.py
docs2vecs/_version.py
docs2vecs/app.py
docs2vecs/cli.py
docs2vecs/core.py
docs2vecs/readers/__init__.py
docs2vecs/readers/yaml.py
docs2vecs/static/app.js
docs2vecs/static/index.html
docs2vecs/static/styles.css
docs2vecs/subcommands/indexer/__init__.py
docs2vecs/subcommands/indexer/indexer.py
docs2vecs/subcommands/indexer/config/__init__.py
docs2vecs/subcommands/indexer/config/config.py
docs2vecs/subcommands/indexer/config/config_schema.yaml
docs2vecs/subcommands/indexer/db/__init__.py
docs2vecs/subcommands/indexer/db/mongodb.py
docs2vecs/subcommands/indexer/document/__init__.py
docs2vecs/subcommands/indexer/document/chunk.py
docs2vecs/subcommands/indexer/document/document.py
docs2vecs/subcommands/indexer/skills/__init__.py
docs2vecs/subcommands/indexer/skills/ada002_embedding_skill.py
docs2vecs/subcommands/indexer/skills/azure_blob_store_uploader_skill.py
docs2vecs/subcommands/indexer/skills/azure_vector_store_skill.py
docs2vecs/subcommands/indexer/skills/chromadb_vector_store_skill.py
docs2vecs/subcommands/indexer/skills/default_file_reader.py
docs2vecs/subcommands/indexer/skills/document_intelligence_skill.py
docs2vecs/subcommands/indexer/skills/factory.py
docs2vecs/subcommands/indexer/skills/file_scanner_skill.py
docs2vecs/subcommands/indexer/skills/jira_loader_skill.py
docs2vecs/subcommands/indexer/skills/llama_fastembed_embedding_skill.py
docs2vecs/subcommands/indexer/skills/local_document_parser.py
docs2vecs/subcommands/indexer/skills/logger.py
docs2vecs/subcommands/indexer/skills/recursive_character_splitter_skill.py
docs2vecs/subcommands/indexer/skills/scrollwordexporter_skill.py
docs2vecs/subcommands/indexer/skills/semantic_splitter_skill.py
docs2vecs/subcommands/indexer/skills/skill.py
docs2vecs/subcommands/indexer/skills/tracker.py
docs2vecs/subcommands/integrated_vec/integrated_vec.py
docs2vecs/subcommands/integrated_vec/config/config_schema.yaml
docs2vecs-0.0.8.dist-info/METADATA
docs2vecs-0.0.8.dist-info/WHEEL
docs2vecs-0.0.8.dist-info/entry_points.txt
docs2vecs-0.0.8.dist-info/licenses/LICENSE
docs2vecs-0.0.8.dist-info/RECORD
