Metadata-Version: 2.4
Name: docs2vecs
Version: 0.0.8
Summary: A library/cli that allows you to vectorize your data, enabling you to create RAG powered applications.
Author-email: Dorin POMIAN <dorin.pomian@amadeus.com>, Waldek HERKA <waldek.herka@amadeus.com>
License-File: LICENSE
Requires-Python: >=3.11
Requires-Dist: azure-ai-formrecognizer>=3.3.3
Requires-Dist: azure-search-documents>=11.5.2
Requires-Dist: azure-storage-blob>=12.24.1
Requires-Dist: cerberus>=1.3.7
Requires-Dist: chromadb>=0.6.3
Requires-Dist: jira>=3.8.0
Requires-Dist: langchain-community>=0.3.18
Requires-Dist: langchain-text-splitters>=0.3.6
Requires-Dist: langchain>=0.3.19
Requires-Dist: llama-index-embeddings-azure-openai>=0.3.0
Requires-Dist: llama-index-embeddings-fastembed>=0.3.0
Requires-Dist: llama-index-llms-openai>=0.3.20
Requires-Dist: llama-index-retrievers-bm25>=0.5.2
Requires-Dist: llama-index-vector-stores-chroma>=0.4.1
Requires-Dist: llama-index>=0.12.20
Requires-Dist: markdown>=3.7
Requires-Dist: openpyxl>=3.1.5
Requires-Dist: pymongo>=4.11.1
Requires-Dist: pystemmer>=2.2.0.3
Requires-Dist: pytest>=8.3.4
Requires-Dist: python-docx>=1.1.2
Requires-Dist: python-dotenv>=1.0.1
Requires-Dist: python-pptx>=1.0.2
Requires-Dist: unstructured>=0.14.8
